[
  {
    "id": 1,
    "name": "Alien Marsh",
    "text": "Select Alien Marsh",
    "style": "map1"


  },
  {
    "id": 2,
    "name": "Dark Lands",
    "text": "Select Dark Lands",
    "style": "map2"

  },
  {
    "id": 3,
    "name": "Dead Lands",
    "text": "Select Dead Lands",
    "style": "map3"
  },
  {
    "id": 4,
    "name": "Dry Desert",
    "text": "Select Dry Desert",
    "style": "map4"

  },
  {
    "id": 5,
    "name": "Dust Plains",
    "text": "Select Dust Plains",
    "style": "map5"

  },
  {
    "id": 6,
    "name": "Grassfield",
    "text": "Select Grassfield",
    "style": "map6"

  },
  {
    "id": 7,
    "name": "Io",
    "text": "Select Io",
    "style": "map7"

  },
  {
    "id": 8,
    "name": "Mars",
    "text": "Select Mars",
    "style": "map8"

  },
  {
    "id": 9,
    "name": "Muddy River",
    "text": "Select Muddy River",
    "style": "map9"

  },
  {
    "id": 10,
    "name": "Rock Formations",
    "text": "Select Rock Formations",
    "style": "map10"

  },
  {
    "id": 11,
    "name": "Sand Dunes",
    "text": "Select Sand Dunes",
    "style": "map11"

  },
  {
    "id": 12,
    "name": "Shallow Sea",
    "text": "Select Shallow Sea",
    "style": "map12"

  },
  {
    "id": 13,
    "name": "Venus",
    "text": "Select Venus",
    "style": "map13"

  },
  {
    "id": 14,
    "name": "Wasteland",
    "text": "Select Wasteland",
    "style": "map14"

  },
  {
    "id": 15,
    "name": "Wetlands",
    "text": "Select Wetlands",
    "style": "map15"

  }
]